[
  {
    "start_time": 0,
    "end_time": 1.671999999999997,
    "content": "你们都太啰嗦了"
  },
  {
    "start_time": 0,
    "end_time": 4.5120000000000005,
    "content": "我要你明媚不要轻易流泪"
  },
  {
    "start_time": 6.311999999999998,
    "end_time": 11.311999999999998,
    "content": "化作树影下斑驳的美"
  },
  {
    "start_time": 9.751999999999995,
    "end_time": 14.751999999999995,
    "content": "恣意摇晃着微风吹"
  },
  {
    "start_time": 13.232,
    "end_time": 18.232,
    "content": "我要你明媚不要轻易流泪"
  },
  {
    "start_time": 20.072000000000003,
    "end_time": 25.072000000000003,
    "content": "卷起浪花闪烁的机会"
  },
  {
    "start_time": 23.912000000000006,
    "end_time": 28.032,
    "content": "橙色落日纷飞"
  }
]